citam_pydraw/__init__.py
citam_pydraw/draw.py
citam_pydraw/keyboard.py
citam_pydraw/mouse.py
citam_pydraw-3.2.2.dist-info/licenses/LICENSE.txt
citam_pydraw-3.2.2.dist-info/WHEEL
citam_pydraw-3.2.2.dist-info/METADATA
citam_pydraw-3.2.2.dist-info/RECORD
