Metadata-Version: 2.4
Name: citam_pydraw
Version: 3.2.2
Summary: CIT-AM Introduction Programming class lib
Author-email: Nao Yamanouchi <nao.yamanouchi@ga.aais-lab.org>
Maintainer-email: Nao Yamanouchi <nao.yamanouchi@ga.aais-lab.org>
Requires-Python:  >= 3.10.5
License-Expression: BSD-3-Clause
Classifier: Programming Language :: Python
Classifier: Programming Language :: Python :: 3.10
Classifier: Programming Language :: Python :: 3.11
Classifier: Programming Language :: Python :: 3.12
Classifier: Programming Language :: Python :: 3 :: Only
Classifier: Operating System :: MacOS
License-File: LICENSE.txt
Requires-Dist: pillow >=11.2
Requires-Dist: just_playback >=0.1.8
Project-URL: Documentation, https://github.com/aais-lab/citam_pydraw/wiki
Project-URL: Issues, https://github.com/aais-lab/citam_pydraw/issues
Project-URL: Source, https://github.com/aais-lab/citam_pydraw.git
